<?xml version="1.0" encoding="UTF-8"?>
<jcamp><type>jcamp</type><title/><jcampdx>5.00</jcampdx><tic>6961980.000000</tic><datatype>MASS SPECTRUM</datatype><dataclass>PEAK TABLE</dataclass><origin/><owner/><npoints>211</npoints><firstx>20.00000000</firstx><lastx>248.00000000</lastx><maxx>248.00000000</maxx><minx>20.00000000</minx><maxy>10000.00000000</maxy><miny>0.01552393</miny><xfactor>1.0000000000</xfactor><yfactor>1.000000000000000</yfactor><firsty>12.60543346</firsty><xunits>M/Z</xunits><yunits>RELATIVE ABUNDANCE</yunits><peaktable>(XY..XY)</peaktable><data><set><type>PEAKTABLE</type><format>(XY..XY)</format><asdftype/><raw><line>20, 12.605433 21, 1.588616 22, 2.354463 24, 1.800776 26, 274.514866 28, 4178.525543</line><line>30, 10000 32, 198.214757 34, 1.371281 36, 81.228983 39, 373.091865 41, 660.284615</line><line>42, 225.097036 43, 133.479953 44, 67.451483 46, 3.826649 47, 0.509702 48, 3.73868</line><line>51, 87.891334 52, 76.222509 54, 246.908164 55, 24.972834 56, 127.839589</line><line>58, 90.349287 59, 983.441162 60, 5.099612 62, 1.839586 63, 2.587322 64, 2.543338</line><line>65, 2.28978 66, 2.168176 67, 2.652005 68, 2.245796 69, 3.586029 70, 4.315653</line><line>71, 1.01423 72, 9.927555 73, 11.994825 74, 1.575679 75, 1.904269 76, 2.150065</line><line>77, 2.732212 78, 2.721863 79, 2.181113 80, 1.358344 81, 1.376455 82, 1.319534</line><line>83, 1.148771 84, 1.345407 85, 0.592497 86, 1.386805 87, 0.69599 88, 0.677878</line><line>89, 1.063389 90, 0.729625 91, 2.468305 92, 0.677878 93, 1.557568 94, 1.404916</line><line>95, 1.384217 96, 1.829237 97, 0.595084 98, 0.719276 99, 0.892626 100, 0.654593</line><line>101, 0.489004 102, 1.076326 103, 1.355757 104, 1.430789 105, 1.363519 106, 1.021992</line><line>107, 0.882277 108, 0.773609 109, 0.54075 110, 0.732212 112, 0.527814 113, 0.600259</line><line>114, 0.747736 115, 1.598965 116, 0.895213 117, 1.13066 118, 0.778784 119, 1.006468</line><line>120, 0.121604 121, 0.620957 122, 0.610608 123, 0.424321 124, 0.486417 125, 0.300129</line><line>126, 0.553687 127, 1.029754 128, 1.047865 129, 0.928849 130, 0.921087 131, 1.151358</line><line>132, 0.548512 133, 0.76326 134, 0.238034 135, 0.913325 136, 0.419146 137, 0.175938</line><line>138, 0.478655 139, 0.51229 140, 0.248383 141, 0.745149 142, 0.641656 143, 0.688228</line><line>144, 0.561449 145, 0.57956 146, 0.543338 147, 0.491591 148, 0.375162 149, 0.452781</line><line>150, 0.517464 151, 0.527814 152, 0.662354 153, 0.605433 154, 0.064683 155, 0.633894</line><line>156, 0.489004 157, 0.496766 158, 0.206986 159, 0.455369 160, 0.320828 161, 0.364812</line><line>162, 0.320828 163, 0.32859 164, 0.338939 165, 0.874515 166, 0.509702 167, 0.57956</line><line>169, 0.439845 170, 0.271669 171, 0.553687 172, 0.25097 173, 0.245796 174, 0.258732</line><line>175, 0.300129 176, 0.32859 177, 0.364812 178, 0.57956 179, 0.548512 180, 0.349289</line><line>181, 0.388098 182, 0.341527 183, 0.318241 184, 0.227684 185, 0.235446 186, 0.015524</line><line>187, 0.401035 188, 0.240621 189, 0.463131 190, 0.238034 191, 0.509702 192, 0.608021</line><line>193, 0.359638 194, 0.32859 195, 0.437257 196, 0.359638 197, 0.025873 198, 0.214748</line><line>199, 0.219922 200, 0.346701 201, 0.331177 202, 0.338939 203, 0.287193 204, 0.320828</line><line>205, 0.520052 206, 0.57956 207, 1.037516 208, 0.442432 209, 0.377749 210, 0.113842</line><line>211, 0.248383 212, 0.206986 213, 0.201811 214, 0.175938 215, 0.305304 216, 0.235446</line><line>217, 0.258732 218, 0.302717 219, 0.545925 220, 0.307891 221, 0.209573 222, 0.300129</line><line>223, 0.253558 224, 0.191462 225, 0.023286 226, 0.315653 227, 0.227684 228, 0.258732</line><line>229, 0.206986 230, 0.191462 231, 0.191462 232, 0.188875 233, 0.186287 234, 0.155239</line><line>235, 0.163001 236, 0.276843 237, 0.051746 238, 0.178525 239, 0.419146 240, 0.134541</line><line>241, 0.305304 242, 0.121604 243, 0.147477 244, 0.186287 245, 0.157827 246, 0.108668</line><line>247, 0.14489 248, 0.139715</line></raw><pro><xy>20,12.605433</xy><xy>21,1.588616</xy><xy>22,2.354463</xy><xy>24,1.800776</xy><xy>26,274.514866</xy><xy>28,4178.525543</xy><xy>30,10000</xy><xy>32,198.214757</xy><xy>34,1.371281</xy><xy>36,81.228983</xy><xy>39,373.091865</xy><xy>41,660.284615</xy><xy>42,225.097036</xy><xy>43,133.479953</xy><xy>44,67.451483</xy><xy>46,3.826649</xy><xy>47,0.509702</xy><xy>48,3.73868</xy><xy>51,87.891334</xy><xy>52,76.222509</xy><xy>54,246.908164</xy><xy>55,24.972834</xy><xy>56,127.839589</xy><xy>58,90.349287</xy><xy>59,983.441162</xy><xy>60,5.099612</xy><xy>62,1.839586</xy><xy>63,2.587322</xy><xy>64,2.543338</xy><xy>65,2.28978</xy><xy>66,2.168176</xy><xy>67,2.652005</xy><xy>68,2.245796</xy><xy>69,3.586029</xy><xy>70,4.315653</xy><xy>71,1.01423</xy><xy>72,9.927555</xy><xy>73,11.994825</xy><xy>74,1.575679</xy><xy>75,1.904269</xy><xy>76,2.150065</xy><xy>77,2.732212</xy><xy>78,2.721863</xy><xy>79,2.181113</xy><xy>80,1.358344</xy><xy>81,1.376455</xy><xy>82,1.319534</xy><xy>83,1.148771</xy><xy>84,1.345407</xy><xy>85,0.592497</xy><xy>86,1.386805</xy><xy>87,0.69599</xy><xy>88,0.677878</xy><xy>89,1.063389</xy><xy>90,0.729625</xy><xy>91,2.468305</xy><xy>92,0.677878</xy><xy>93,1.557568</xy><xy>94,1.404916</xy><xy>95,1.384217</xy><xy>96,1.829237</xy><xy>97,0.595084</xy><xy>98,0.719276</xy><xy>99,0.892626</xy><xy>100,0.654593</xy><xy>101,0.489004</xy><xy>102,1.076326</xy><xy>103,1.355757</xy><xy>104,1.430789</xy><xy>105,1.363519</xy><xy>106,1.021992</xy><xy>107,0.882277</xy><xy>108,0.773609</xy><xy>109,0.54075</xy><xy>110,0.732212</xy><xy>112,0.527814</xy><xy>113,0.600259</xy><xy>114,0.747736</xy><xy>115,1.598965</xy><xy>116,0.895213</xy><xy>117,1.13066</xy><xy>118,0.778784</xy><xy>119,1.006468</xy><xy>120,0.121604</xy><xy>121,0.620957</xy><xy>122,0.610608</xy><xy>123,0.424321</xy><xy>124,0.486417</xy><xy>125,0.300129</xy><xy>126,0.553687</xy><xy>127,1.029754</xy><xy>128,1.047865</xy><xy>129,0.928849</xy><xy>130,0.921087</xy><xy>131,1.151358</xy><xy>132,0.548512</xy><xy>133,0.76326</xy><xy>134,0.238034</xy><xy>135,0.913325</xy><xy>136,0.419146</xy><xy>137,0.175938</xy><xy>138,0.478655</xy><xy>139,0.51229</xy><xy>140,0.248383</xy><xy>141,0.745149</xy><xy>142,0.641656</xy><xy>143,0.688228</xy><xy>144,0.561449</xy><xy>145,0.57956</xy><xy>146,0.543338</xy><xy>147,0.491591</xy><xy>148,0.375162</xy><xy>149,0.452781</xy><xy>150,0.517464</xy><xy>151,0.527814</xy><xy>152,0.662354</xy><xy>153,0.605433</xy><xy>154,0.064683</xy><xy>155,0.633894</xy><xy>156,0.489004</xy><xy>157,0.496766</xy><xy>158,0.206986</xy><xy>159,0.455369</xy><xy>160,0.320828</xy><xy>161,0.364812</xy><xy>162,0.320828</xy><xy>163,0.32859</xy><xy>164,0.338939</xy><xy>165,0.874515</xy><xy>166,0.509702</xy><xy>167,0.57956</xy><xy>169,0.439845</xy><xy>170,0.271669</xy><xy>171,0.553687</xy><xy>172,0.25097</xy><xy>173,0.245796</xy><xy>174,0.258732</xy><xy>175,0.300129</xy><xy>176,0.32859</xy><xy>177,0.364812</xy><xy>178,0.57956</xy><xy>179,0.548512</xy><xy>180,0.349289</xy><xy>181,0.388098</xy><xy>182,0.341527</xy><xy>183,0.318241</xy><xy>184,0.227684</xy><xy>185,0.235446</xy><xy>186,0.015524</xy><xy>187,0.401035</xy><xy>188,0.240621</xy><xy>189,0.463131</xy><xy>190,0.238034</xy><xy>191,0.509702</xy><xy>192,0.608021</xy><xy>193,0.359638</xy><xy>194,0.32859</xy><xy>195,0.437257</xy><xy>196,0.359638</xy><xy>197,0.025873</xy><xy>198,0.214748</xy><xy>199,0.219922</xy><xy>200,0.346701</xy><xy>201,0.331177</xy><xy>202,0.338939</xy><xy>203,0.287193</xy><xy>204,0.320828</xy><xy>205,0.520052</xy><xy>206,0.57956</xy><xy>207,1.037516</xy><xy>208,0.442432</xy><xy>209,0.377749</xy><xy>210,0.113842</xy><xy>211,0.248383</xy><xy>212,0.206986</xy><xy>213,0.201811</xy><xy>214,0.175938</xy><xy>215,0.305304</xy><xy>216,0.235446</xy><xy>217,0.258732</xy><xy>218,0.302717</xy><xy>219,0.545925</xy><xy>220,0.307891</xy><xy>221,0.209573</xy><xy>222,0.300129</xy><xy>223,0.253558</xy><xy>224,0.191462</xy><xy>225,0.023286</xy><xy>226,0.315653</xy><xy>227,0.227684</xy><xy>228,0.258732</xy><xy>229,0.206986</xy><xy>230,0.191462</xy><xy>231,0.191462</xy><xy>232,0.188875</xy><xy>233,0.186287</xy><xy>234,0.155239</xy><xy>235,0.163001</xy><xy>236,0.276843</xy><xy>237,0.051746</xy><xy>238,0.178525</xy><xy>239,0.419146</xy><xy>240,0.134541</xy><xy>241,0.305304</xy><xy>242,0.121604</xy><xy>243,0.147477</xy><xy>244,0.186287</xy><xy>245,0.157827</xy><xy>246,0.108668</xy><xy>247,0.14489</xy><xy>248,0.139715</xy></pro></set></data><end/><datetime>1999-11-30T00:00:00-05:00</datetime><params/><bruker/><comments><ldr_title>Begin of the data block</ldr_title><ldr_jcampdx>ACD/SpecManager v 12.01</ldr_jcampdx><ldr_maxx>Max X corrected Stuart Chalk 8/14/15</ldr_maxx><ldr_minx>Min X corrected Stuart Chalk 8/14/15</ldr_minx><ldr_maxy>Max Y corrected Stuart Chalk 8/14/15</ldr_maxy><ldr_miny>Min Y corrected Stuart Chalk 8/14/15</ldr_miny><ldr_end>End of the data block</ldr_end></comments><errors/></jcamp>
